{
    "question": {
        "owner": {
            "profile_image": "https://www.gravatar.com/avatar/528cabb7e6c44144423d527a2c54786e?s=256&d=identicon&r=PG&f=y&so-version=2",
            "account_id": 5265366,
            "user_type": "registered",
            "user_id": 4205542,
            "link": "https://stackoverflow.com/users/4205542/arm",
            "reputation": 317,
            "display_name": "ArM",
            "accept_rate": 67
        },
        "content_license": "CC BY-SA 3.0",
        "link": "https://stackoverflow.com/questions/41318966/are-class-level-static-blocks-represented-as-methods-in-byte-code",
        "last_activity_date": 1482648378,
        "creation_date": 1482644790,
        "answer_count": 2,
        "title": "Are class-level static blocks represented as methods in byte code?",
        "body": "<p>I created a small Java class and ran the <code>javap<\/code> command against the corresponding .class file. I'm just doing this in an effort to understand how the class file is organized (yes, I've been going through the JVM specs too). I could be wrong, but from what I understand of the class file structure. it seems that the class-level static block is being listed as a method. <\/p>\n\n<p>Am I interpreting this correctly (that the static block is being represented as a method)? If yes, is a static block somehow considered equivalent to a method in Java?<\/p>\n\n<p><strong>Source file:<\/strong><\/p>\n\n<pre><code>package test;\n\npublic class TestClass\n{\n    static {\n        System.out.println(\"abcd\");\n    }\n\n    public void method(String s)\n    {\n        System.out.println(\"hello world\");\n    }\n}\n<\/code><\/pre>\n\n<p><strong><code>javap<\/code> output:<\/strong><\/p>\n\n<pre><code>Classfile /C:/TestClass.class\n  Last modified Dec 25, 2016; size 477 bytes\n  MD5 checksum 7571c8f98e814fb8bb53885f073c6048\n  Compiled from \"TestClass.java\"\npublic class test.TestClass\n  minor version: 0\n  major version: 52\n  flags: ACC_PUBLIC, ACC_SUPER\nConstant pool:\n   #1 = Methodref          #7.#17         // java/lang/Object.\"&lt;init&gt;\":()V\n   #2 = Fieldref           #18.#19        // java/lang/System.out:Ljava/io/PrintStream;\n   #3 = String             #20            // hello world\n   #4 = Methodref          #21.#22        // java/io/PrintStream.println:(Ljava/lang/String;)V\n   #5 = String             #23            // abcd\n   #6 = Class              #24            // test/TestClass\n   #7 = Class              #25            // java/lang/Object\n   #8 = Utf8               &lt;init&gt;\n   #9 = Utf8               ()V\n  #10 = Utf8               Code\n  #11 = Utf8               LineNumberTable\n  #12 = Utf8               method\n  #13 = Utf8               (Ljava/lang/String;)V\n  #14 = Utf8               &lt;clinit&gt;\n  #15 = Utf8               SourceFile\n  #16 = Utf8               TestClass.java\n  #17 = NameAndType        #8:#9          // \"&lt;init&gt;\":()V\n  #18 = Class              #26            // java/lang/System\n  #19 = NameAndType        #27:#28        // out:Ljava/io/PrintStream;\n  #20 = Utf8               hello world\n  #21 = Class              #29            // java/io/PrintStream\n  #22 = NameAndType        #30:#13        // println:(Ljava/lang/String;)V\n  #23 = Utf8               abcd\n  #24 = Utf8               test/TestClass\n  #25 = Utf8               java/lang/Object\n  #26 = Utf8               java/lang/System\n  #27 = Utf8               out\n  #28 = Utf8               Ljava/io/PrintStream;\n  #29 = Utf8               java/io/PrintStream\n  #30 = Utf8               println\n{\n  public test.TestClass();\n    descriptor: ()V\n    flags: ACC_PUBLIC\n    Code:\n      stack=1, locals=1, args_size=1\n         0: aload_0\n         1: invokespecial #1                  // Method java/lang/Object.\"&lt;init&gt;\":()V\n         4: return\n      LineNumberTable:\n        line 3: 0\n\n  public void method(java.lang.String);\n    descriptor: (Ljava/lang/String;)V\n    flags: ACC_PUBLIC\n    Code:\n      stack=2, locals=2, args_size=2\n         0: getstatic     #2                  // Field java/lang/System.out:Ljava/io/PrintStream;\n         3: ldc           #3                  // String hello world\n         5: invokevirtual #4                  // Method java/io/PrintStream.println:(Ljava/lang/String;)V\n         8: return\n      LineNumberTable:\n        line 11: 0\n        line 12: 8\n\n  static {};\n    descriptor: ()V\n    flags: ACC_STATIC\n    Code:\n      stack=2, locals=0, args_size=0\n         0: getstatic     #2                  // Field java/lang/System.out:Ljava/io/PrintStream;\n         3: ldc           #5                  // String abcd\n         5: invokevirtual #4                  // Method java/io/PrintStream.println:(Ljava/lang/String;)V\n         8: return\n      LineNumberTable:\n        line 6: 0\n        line 7: 8\n}\nSourceFile: \"TestClass.java\"\n<\/code><\/pre>\n",
        "question_id": 41318966,
        "tags": [
            "java",
            "bytecode"
        ],
        "score": 2,
        "is_answered": true,
        "view_count": 469
    },
    "question_comments": [
        {
            "owner": {
                "profile_image": "https://i.sstatic.net/gWI7z.png?s=256",
                "account_id": 202717,
                "user_type": "registered",
                "user_id": 449946,
                "link": "https://stackoverflow.com/users/449946/firephil",
                "reputation": 866,
                "display_name": "firephil",
                "accept_rate": 100
            },
            "content_license": "CC BY-SA 3.0",
            "score": 1,
            "post_id": 41318966,
            "reply_to_user": {
                "profile_image": "https://www.gravatar.com/avatar/b31ee54d9d3789bf16fe971dbb4a2ef8?s=256&d=identicon&r=PG&f=y&so-version=2",
                "account_id": 9760,
                "user_type": "registered",
                "user_id": 18157,
                "link": "https://stackoverflow.com/users/18157/jim-garrison",
                "reputation": 87027,
                "display_name": "Jim Garrison",
                "accept_rate": 100
            },
            "edited": false,
            "creation_date": 1482776421,
            "comment_id": 69872308
        },
        {
            "owner": {
                "profile_image": "https://www.gravatar.com/avatar/b31ee54d9d3789bf16fe971dbb4a2ef8?s=256&d=identicon&r=PG&f=y&so-version=2",
                "account_id": 9760,
                "user_type": "registered",
                "user_id": 18157,
                "link": "https://stackoverflow.com/users/18157/jim-garrison",
                "reputation": 87027,
                "display_name": "Jim Garrison",
                "accept_rate": 100
            },
            "content_license": "CC BY-SA 3.0",
            "score": 0,
            "post_id": 41318966,
            "reply_to_user": {
                "profile_image": "https://i.sstatic.net/gWI7z.png?s=256",
                "account_id": 202717,
                "user_type": "registered",
                "user_id": 449946,
                "link": "https://stackoverflow.com/users/449946/firephil",
                "reputation": 866,
                "display_name": "firephil",
                "accept_rate": 100
            },
            "edited": false,
            "creation_date": 1482775412,
            "comment_id": 69871972
        },
        {
            "owner": {
                "profile_image": "https://i.sstatic.net/gWI7z.png?s=256",
                "account_id": 202717,
                "user_type": "registered",
                "user_id": 449946,
                "link": "https://stackoverflow.com/users/449946/firephil",
                "reputation": 866,
                "display_name": "firephil",
                "accept_rate": 100
            },
            "content_license": "CC BY-SA 3.0",
            "score": 0,
            "post_id": 41318966,
            "reply_to_user": {
                "profile_image": "https://www.gravatar.com/avatar/b31ee54d9d3789bf16fe971dbb4a2ef8?s=256&d=identicon&r=PG&f=y&so-version=2",
                "account_id": 9760,
                "user_type": "registered",
                "user_id": 18157,
                "link": "https://stackoverflow.com/users/18157/jim-garrison",
                "reputation": 87027,
                "display_name": "Jim Garrison",
                "accept_rate": 100
            },
            "edited": false,
            "creation_date": 1482651977,
            "comment_id": 69842554
        },
        {
            "owner": {
                "profile_image": "https://www.gravatar.com/avatar/b31ee54d9d3789bf16fe971dbb4a2ef8?s=256&d=identicon&r=PG&f=y&so-version=2",
                "account_id": 9760,
                "user_type": "registered",
                "user_id": 18157,
                "link": "https://stackoverflow.com/users/18157/jim-garrison",
                "reputation": 87027,
                "display_name": "Jim Garrison",
                "accept_rate": 100
            },
            "content_license": "CC BY-SA 3.0",
            "score": 1,
            "post_id": 41318966,
            "edited": false,
            "creation_date": 1482645912,
            "comment_id": 69841730
        }
    ],
    "answers": [
        {
            "owner": {
                "profile_image": "https://www.gravatar.com/avatar/c799e8b3d14c4f149ce71455109f17eb?s=256&d=identicon&r=PG",
                "account_id": 1520477,
                "user_type": "registered",
                "user_id": 1420279,
                "link": "https://stackoverflow.com/users/1420279/antimony",
                "reputation": 39806,
                "display_name": "Antimony",
                "accept_rate": 80
            },
            "content_license": "CC BY-SA 3.0",
            "score": 2,
            "is_accepted": false,
            "last_activity_date": 1482648378,
            "creation_date": 1482648378,
            "body": "<p>There are two types of initializers in Java, instance and static. <\/p>\n\n<p>At the bytecode level, all of the static initializers (plus initialization of static fields that are nonfinal or initialized to a nonconstant expression) are compiled and concatenated into one method, called <code>&lt;clinit&gt;<\/code>. This is a special method which is called automatically by the JVM after a class is loaded but can't be called by normal code. Note that no matter how many seperate static initializer blocks you have at the source code level, there is only one clinit method.<\/p>\n\n<p>Instance initalizers don't have a direct equivalent in bytecode. All the instance initializers, plus initializers of instance fields, are compiled and inserted into the classes constructor methods right after returning from the superclass constructor call. Incidently, this means it is possible to observe an instance's state prior to the initalizers being invoked, which is why you shouldn't call virtual methods from a constructor.<\/p>\n",
            "answer_id": 41319207,
            "question_id": 41318966
        },
        {
            "owner": {
                "profile_image": "https://www.gravatar.com/avatar/3a6b947cd4c65dce0c3493549f9f411c?s=256&d=identicon&r=PG",
                "account_id": 535619,
                "user_type": "registered",
                "user_id": 905033,
                "link": "https://stackoverflow.com/users/905033/lew-bloch",
                "reputation": 3446,
                "display_name": "Lew Bloch"
            },
            "content_license": "CC BY-SA 3.0",
            "score": 0,
            "is_accepted": false,
            "last_activity_date": 1482647025,
            "creation_date": 1482647025,
            "body": "<p>It isn't exactly a method, it's an initializer, like a constructor but at the class level. \"Static block\" isn't the right term; it's \"static initializer block\", so it makes sense. It is as much or little like a void method as a constructor is.<\/p>\n",
            "answer_id": 41319119,
            "question_id": 41318966
        }
    ],
    "answer_comments": {}
}